asyncgui.py
asyncgui-0.9.1.dist-info/LICENSE
asyncgui-0.9.1.dist-info/METADATA
asyncgui-0.9.1.dist-info/WHEEL
asyncgui-0.9.1.dist-info/RECORD
