Metadata-Version: 2.3
Name: asyncgui
Version: 0.9.1
Summary: A minimalistic async library that focuses on fast responsiveness
License: MIT
Keywords: async
Author: Nattōsai Mitō
Author-email: flow4re2c@gmail.com
Requires-Python: >=3.9,<4.0
Classifier: Development Status :: 5 - Production/Stable
Classifier: Intended Audience :: Developers
Classifier: License :: OSI Approved :: MIT License
Classifier: Operating System :: OS Independent
Classifier: Programming Language :: Python
Classifier: Programming Language :: Python :: 3
Classifier: Programming Language :: Python :: 3.9
Classifier: Programming Language :: Python :: 3.10
Classifier: Programming Language :: Python :: 3.11
Classifier: Programming Language :: Python :: 3.12
Classifier: Programming Language :: Python :: 3.13
Classifier: Topic :: Software Development :: Libraries
Requires-Dist: exceptiongroup (>=1.0.4,<2.0.0) ; python_version < "3.11"
Project-URL: Homepage, https://github.com/asyncgui/asyncgui
Project-URL: Repository, https://github.com/asyncgui/asyncgui
